versionix/__init__.py
versionix/blacklist.py
versionix/logging.py
versionix/parser.py
versionix/registry.py
versionix/scripts.py
versionix-0.99.3.dist-info/LICENSE
versionix-0.99.3.dist-info/METADATA
versionix-0.99.3.dist-info/WHEEL
versionix-0.99.3.dist-info/entry_points.txt
versionix-0.99.3.dist-info/RECORD
